azureipcheck/__init__.py
azureipcheck/__main__.py
azureipcheck/callbacks.py
azureipcheck/constants.py
azureipcheck/main.py
azureipcheck/styles.py
azureipcheck/utils.py
azureipcheck-1.0.1.dist-info/entry_points.txt
azureipcheck-1.0.1.dist-info/WHEEL
azureipcheck-1.0.1.dist-info/METADATA
azureipcheck-1.0.1.dist-info/RECORD
