Metadata-Version: 2.1
Name: azureipcheck
Version: 1.0.1
Summary: A Python CLI tool to check service tags for Azure IPs
Home-page: https://github.com/daddycocoaman/azureipcheck
License: MIT
Author: Leron Gray
Requires-Python: >=3.8,<4.0
Classifier: License :: OSI Approved :: MIT License
Classifier: Programming Language :: Python :: 3
Classifier: Programming Language :: Python :: 3.8
Classifier: Programming Language :: Python :: 3.9
Requires-Dist: click-help-colors (>=0.9,<0.10)
Requires-Dist: clumper (>=0.2.7,<0.3.0)
Requires-Dist: gazpacho (>=1.1,<2.0)
Requires-Dist: rich (>=9.3.0,<10.0.0)
Requires-Dist: typer[all] (>=0.3.2,<0.4.0)
